file_keeper/__init__.py
file_keeper/core/__init__.py
file_keeper/core/data.py
file_keeper/core/exceptions.py
file_keeper/core/registry.py
file_keeper/core/storage.py
file_keeper/core/types.py
file_keeper/core/upload.py
file_keeper/core/utils.py
file_keeper/default/__init__.py
file_keeper/default/adapters/__init__.py
file_keeper/default/adapters/filebin.py
file_keeper/default/adapters/fs.py
file_keeper/default/adapters/gcs.py
file_keeper/default/adapters/libcloud.py
file_keeper/default/adapters/opendal.py
file_keeper/default/adapters/redis.py
file_keeper/default/adapters/s3.py
file_keeper/default/adapters/sqlalchemy.py
file_keeper/ext/__init__.py
file_keeper/ext/spec.py
file_keeper-0.0.10.dist-info/METADATA
file_keeper-0.0.10.dist-info/WHEEL
file_keeper-0.0.10.dist-info/entry_points.txt
file_keeper-0.0.10.dist-info/top_level.txt
file_keeper-0.0.10.dist-info/RECORD
